whylogs_container_types/__init__.py
whylogs_container_types-0.4.16.dist-info/METADATA
whylogs_container_types-0.4.16.dist-info/WHEEL
whylogs_container_types-0.4.16.dist-info/RECORD
