Metadata-Version: 2.1
Name: whylogs-container-types
Version: 0.4.16
Summary: 
License: MIT
Author: Anthony Naddeo
Author-email: anthony@whylabs.ai
Requires-Python: >=3.8,<4.0
Classifier: License :: OSI Approved :: MIT License
Classifier: Programming Language :: Python :: 3
Classifier: Programming Language :: Python :: 3.8
Classifier: Programming Language :: Python :: 3.9
Classifier: Programming Language :: Python :: 3.10
Classifier: Programming Language :: Python :: 3.11
Classifier: Programming Language :: Python :: 3.12
Requires-Dist: langkit (==0.0.28.*)
Requires-Dist: whylogs
